rignore-0.7.5.dist-info/METADATA
rignore-0.7.5.dist-info/WHEEL
rignore-0.7.5.dist-info/licenses/LICENSE
rignore/__init__.py
rignore/__init__.pyi
rignore/py.typed
rignore/rignore.cpython-314-powerpc64le-linux-gnu.so
rignore-0.7.5.dist-info/RECORD
