Metadata-Version: 2.4
Name: rignore
Version: 0.7.5
Classifier: Programming Language :: Rust
Classifier: Programming Language :: Python :: Implementation :: CPython
Classifier: Programming Language :: Python :: Implementation :: PyPy
License-File: LICENSE
Summary: Python Bindings for the ignore crate
Author-email: Patrick Arminio <patrick.arminio@gmail.com>
License: MIT
Requires-Python: >=3.8
